commonroad_velocity_planner/__init__.py
commonroad_velocity_planner/behavior/__init__.py
commonroad_velocity_planner/behavior/speed_limits.py
commonroad_velocity_planner/configuration/__init__.py
commonroad_velocity_planner/configuration/configuration_builder.py
commonroad_velocity_planner/configuration/optimization_config.py
commonroad_velocity_planner/configuration/vehicle_config.py
commonroad_velocity_planner/configuration/velocity_planner_config.py
commonroad_velocity_planner/fast_api.py
commonroad_velocity_planner/global_trajectory.py
commonroad_velocity_planner/planner/__init__.py
commonroad_velocity_planner/planner/bang_bang_planner.py
commonroad_velocity_planner/planner/base_planner.py
commonroad_velocity_planner/planner/lp_optimization_planner.py
commonroad_velocity_planner/planner/qp_optimization_planner.py
commonroad_velocity_planner/preprocessing/__init__.py
commonroad_velocity_planner/preprocessing/adaptive_sampling.py
commonroad_velocity_planner/preprocessing/curvature_smoother.py
commonroad_velocity_planner/preprocessing/elastic_band_algo.py
commonroad_velocity_planner/solver_interface/__init__.py
commonroad_velocity_planner/solver_interface/cvxpy_interface.py
commonroad_velocity_planner/spline_profile.py
commonroad_velocity_planner/utils/__init__.py
commonroad_velocity_planner/utils/exceptions.py
commonroad_velocity_planner/utils/jerk_filter.py
commonroad_velocity_planner/utils/max_velocity_calc.py
commonroad_velocity_planner/utils/planning_problem.py
commonroad_velocity_planner/utils/polyline_operations.py
commonroad_velocity_planner/utils/regulatory_elements.py
commonroad_velocity_planner/utils/visualization/__init__.py
commonroad_velocity_planner/utils/visualization/visualize_acceleration.py
commonroad_velocity_planner/utils/visualization/visualize_quantities.py
commonroad_velocity_planner/utils/visualization/visualize_velocity_planner.py
commonroad_velocity_planner/velocity_planner_interface.py
commonroad_velocity_planner-1.0.0.dist-info/LICENSE
commonroad_velocity_planner-1.0.0.dist-info/METADATA
commonroad_velocity_planner-1.0.0.dist-info/WHEEL
commonroad_velocity_planner-1.0.0.dist-info/RECORD
