Metadata-Version: 2.3
Name: commonroad-velocity-planner
Version: 1.0.0
Summary: CommonRoad Velocity Planner Toolbox
License: BSD
Keywords: autonomous,automated,vehicles,driving,motion,planning,velocity
Author: Tobias Mascetta
Author-email: <tobias.mascetta@tum.de>
Requires-Python: >=3.9,<3.12
Classifier: Programming Language :: Python :: 3.9
Classifier: License :: OSI Approved :: BSD License
Classifier: Operating System :: POSIX :: Linux
Requires-Dist: commonroad-io (>=2022.2)
Requires-Dist: commonroad-route-planner (>=2025.0.1,<2026.0.0)
Requires-Dist: cvxpy (>=1.4,<2.0)
Requires-Dist: matplotlib (<3.9)
Requires-Dist: numpy (>=1.17.4,<2.0)
